nestedquery/__init__.py
django_nestedquery-0.2.0.dist-info/METADATA
django_nestedquery-0.2.0.dist-info/WHEEL
django_nestedquery-0.2.0.dist-info/top_level.txt
django_nestedquery-0.2.0.dist-info/RECORD
