Metadata-Version: 2.1
Name: django-nestedquery
Version: 0.2.0
Summary: Django Nested Query
Author-email: Simage <simage@gmail.com>
Requires-Python: >=3.8
Requires-Dist: django (<4.0.0,>=3.1)
